ctxssg/__init__.py
ctxssg/__main__.py
ctxssg/cli.py
ctxssg/config.py
ctxssg/content.py
ctxssg/formats.py
ctxssg/generator.py
ctxssg/resources.py
ctxssg-0.1.0.dist-info/licenses/LICENSE
ctxssg-0.1.0.dist-info/METADATA
ctxssg-0.1.0.dist-info/WHEEL
ctxssg-0.1.0.dist-info/entry_points.txt
ctxssg-0.1.0.dist-info/top_level.txt
ctxssg-0.1.0.dist-info/RECORD
