Metadata-Version: 2.4
Name: ctxssg
Version: 0.1.0
Summary: contextual docs
Author: Kyle Gruel
License-Expression: Apache-2.0
Project-URL: Homepage, https://github.com/kgruel/ctxssg
Project-URL: Changelog, https://github.com/kgruel/ctxssg/releases
Project-URL: Issues, https://github.com/kgruel/ctxssg/issues
Project-URL: CI, https://github.com/kgruel/ctxssg/actions
Requires-Python: >=3.10
License-File: LICENSE
Requires-Dist: click>=8.0
Requires-Dist: pypandoc>=1.11
Requires-Dist: pyyaml>=6.0
Requires-Dist: jinja2>=3.0
Requires-Dist: watchdog>=3.0
Requires-Dist: python-frontmatter>=1.0
Requires-Dist: beautifulsoup4>=4.12
Requires-Dist: tomli>=2.0.0; python_version < "3.11"
Provides-Extra: test
Requires-Dist: pytest; extra == "test"
Dynamic: license-file
